topsis/__init__.py
topsis/topsis.py
topsis_vardhan_102203268-1.0.3.dist-info/LICENSE
topsis_vardhan_102203268-1.0.3.dist-info/METADATA
topsis_vardhan_102203268-1.0.3.dist-info/WHEEL
topsis_vardhan_102203268-1.0.3.dist-info/entry_points.txt
topsis_vardhan_102203268-1.0.3.dist-info/top_level.txt
topsis_vardhan_102203268-1.0.3.dist-info/RECORD
