Metadata-Version: 2.1
Name: topsis-vardhan-102203268
Version: 1.0.3
Summary: A Python package to perform TOPSIS (Technique for Order Preference by Similarity to Ideal Solution)
Home-page: https://github.com/vardhan-rawat/topsis_vardhan_102203268
Author: Vardhan Singh Rawat
Author-email: vardhanrawat1@gmail.com
Classifier: Programming Language :: Python :: 3
Classifier: License :: OSI Approved :: MIT License
Classifier: Operating System :: OS Independent
Requires-Python: >=3.6
License-File: LICENSE
Requires-Dist: numpy
Requires-Dist: pandas
